metadownload/__init__.py
metadownload/metadownload.py
metadownload-0.1.3.dist-info/METADATA
metadownload-0.1.3.dist-info/WHEEL
metadownload-0.1.3.dist-info/entry_points.txt
metadownload-0.1.3.dist-info/top_level.txt
metadownload-0.1.3.dist-info/RECORD
