Metadata-Version: 2.1
Name: metadownload
Version: 0.1.3
Summary: python mlst analysis tool
Home-page: https://github.com/hbucqp/metadownload
Author: Qingpo Cui
Author-email: cqp@cau.edu.cn
License: MIT Licence
Keywords: wgs,pubmlst,mlst
Platform: any
Classifier: Development Status :: 3 - Alpha
Classifier: Intended Audience :: Developers
Classifier: Topic :: Software Development :: Build Tools
Classifier: License :: OSI Approved :: MIT License
Classifier: Programming Language :: Python :: 3
Classifier: Programming Language :: Python :: 3.7
Classifier: Programming Language :: Python :: 3.8
Classifier: Programming Language :: Python :: 3.9
Requires-Dist: pandas
Requires-Dist: setuptools
